{"readme.md":"040dcc84","blog_announcing-vite2.md":"51cd44c6","blog_announcing-vite3.md":"e4ba6bfb","config_build-options.md":"7008207c","config_dep-optimization-options.md":"715abd1c","config_index.md":"d7bfdb4e","config_preview-options.md":"04a62fef","config_server-options.md":"4fa3ee6e","config_shared-options.md":"7483c10a","config_ssr-options.md":"dd0015f2","config_worker-options.md":"b951f834","guide_api-hmr.md":"27c137eb","guide_api-javascript.md":"3d944efd","guide_api-plugin.md":"2d4c0ebf","guide_assets.md":"ebcf4d74","guide_backend-integration.md":"cc7be607","guide_booking_concept.md":"f7fb36b0","guide_booking_demo-image.md":"15c3bf7a","guide_booking_features.md":"a41e1bfe","guide_booking_intro.md":"469e7eea","guide_booking_other-info.md":"d0837bc1","guide_booking_start-using.md":"7c30cb08","guide_build.md":"adc1f4da","guide_comparisons.md":"c71f8460","guide_dep-pre-bundling.md":"7b9d39a1","guide_env-and-mode.md":"5718063e","guide_features.md":"c424c6e0","guide_index.md":"767cc07a","guide_migration-from-v1.md":"dc23ece5","guide_migration.md":"e922df6a","guide_ssr.md":"9d6e4200","guide_static-deploy.md":"b10f2283","guide_troubleshooting.md":"bb66e3f3","guide_using-plugins.md":"884f11f9","guide_why.md":"7d4010ac","index.md":"2e50e2d0","plugins_index.md":"d9b26a57","team.md":"a08a04cf"}
